{
  "bids": "v1.1.5",
  "budget": "master",
  "charges": "master",
  "documentation_details": "master",
  "finance": "master",
  "location": "v1.1.5",
  "metrics": "master",
  "milestone_documents": "v1.1.5",
  "performance_failures": "master",
  "process_title": "v1.1.5",
  "project": "master",
  "qualification": "master",
  "requirements": "master",
  "risk_allocation": "master",
  "shareholders": "master",
  "signatories": "master",
  "tariffs": "master",
  "transaction_milestones": "master",
  "ppp": "master"
}
